{
"meta":{"test_sets":[],"test_metrics":[],"learn_metrics":[{"best_value":"Min","name":"RMSE"}],"launch_mode":"Train","parameters":"","iteration_count":100,"learn_sets":["learn"],"name":"experiment"},
"iterations":[
{"learn":[14.26765708],"iteration":0,"passed_time":0.000627594319,"remaining_time":0.06213183758},
{"learn":[13.35984652],"iteration":1,"passed_time":0.001339695721,"remaining_time":0.06564509031},
{"learn":[12.55673832],"iteration":2,"passed_time":0.001885088987,"remaining_time":0.06095121059},
{"learn":[11.91727589],"iteration":3,"passed_time":0.002361895707,"remaining_time":0.05668549696},
{"learn":[11.23579373],"iteration":4,"passed_time":0.002924173578,"remaining_time":0.05555929799},
{"learn":[10.69715691],"iteration":5,"passed_time":0.003442049209,"remaining_time":0.05392543761},
{"learn":[10.15852595],"iteration":6,"passed_time":0.004201140813,"remaining_time":0.05581515651},
{"learn":[9.680420516],"iteration":7,"passed_time":0.004920117904,"remaining_time":0.05658135589},
{"learn":[9.280057546],"iteration":8,"passed_time":0.005496690931,"remaining_time":0.05557765275},
{"learn":[8.809430667],"iteration":9,"passed_time":0.006220234706,"remaining_time":0.05598211236},
{"learn":[8.454214788],"iteration":10,"passed_time":0.007128445385,"remaining_time":0.05767560357},
{"learn":[8.175929562],"iteration":11,"passed_time":0.007731839776,"remaining_time":0.05670015836},
{"learn":[7.874420661],"iteration":12,"passed_time":0.008602997011,"remaining_time":0.05757390308},
{"learn":[7.625417126],"iteration":13,"passed_time":0.009406685009,"remaining_time":0.0577839222},
{"learn":[7.358978676],"iteration":14,"passed_time":0.009918126815,"remaining_time":0.05620271862},
{"learn":[7.140486335],"iteration":15,"passed_time":0.01080971845,"remaining_time":0.05675102188},
{"learn":[6.940309299],"iteration":16,"passed_time":0.01145051814,"remaining_time":0.05590547094},
{"learn":[6.753602269],"iteration":17,"passed_time":0.01204033225,"remaining_time":0.05485040246},
{"learn":[6.597300596],"iteration":18,"passed_time":0.01252889972,"remaining_time":0.05341267776},
{"learn":[6.441714086],"iteration":19,"passed_time":0.01315603804,"remaining_time":0.05262415217},
{"learn":[6.330350997],"iteration":20,"passed_time":0.0136908801,"remaining_time":0.05150378706},
{"learn":[6.209608211],"iteration":21,"passed_time":0.01429393603,"remaining_time":0.05067850047},
{"learn":[6.092350761],"iteration":22,"passed_time":0.01490302036,"remaining_time":0.04989272035},
{"learn":[5.980288492],"iteration":23,"passed_time":0.01548293304,"remaining_time":0.04902928798},
{"learn":[5.892764543],"iteration":24,"passed_time":0.01622799506,"remaining_time":0.04868398517},
{"learn":[5.800193077],"iteration":25,"passed_time":0.0168249493,"remaining_time":0.04788639417},
{"learn":[5.734197753],"iteration":26,"passed_time":0.01756445229,"remaining_time":0.04748907472},
{"learn":[5.67881938],"iteration":27,"passed_time":0.01814500955,"remaining_time":0.04665859598},
{"learn":[5.620364969],"iteration":28,"passed_time":0.01869876478,"remaining_time":0.04577973445},
{"learn":[5.559424251],"iteration":29,"passed_time":0.01929861458,"remaining_time":0.04503010068},
{"learn":[5.508633394],"iteration":30,"passed_time":0.01990170918,"remaining_time":0.0442973527},
{"learn":[5.466289122],"iteration":31,"passed_time":0.02093546015,"remaining_time":0.04448785282},
{"learn":[5.421958221],"iteration":32,"passed_time":0.0217438558,"remaining_time":0.04414661631},
{"learn":[5.386062774],"iteration":33,"passed_time":0.02272956211,"remaining_time":0.04412209115},
{"learn":[5.361780758],"iteration":34,"passed_time":0.02331632928,"remaining_time":0.04330175437},
{"learn":[5.329170639],"iteration":35,"passed_time":0.02384409108,"remaining_time":0.04238949526},
{"learn":[5.297322536],"iteration":36,"passed_time":0.02476484508,"remaining_time":0.04216716865},
{"learn":[5.27726053],"iteration":37,"passed_time":0.02554274199,"remaining_time":0.04167500008},
{"learn":[5.252183926],"iteration":38,"passed_time":0.02611842236,"remaining_time":0.04085189138},
{"learn":[5.228456686],"iteration":39,"passed_time":0.02670975956,"remaining_time":0.04006463934},
{"learn":[5.211606841],"iteration":40,"passed_time":0.02738694283,"remaining_time":0.0394104787},
{"learn":[5.186180958],"iteration":41,"passed_time":0.02807154705,"remaining_time":0.03876546973},
{"learn":[5.163248177],"iteration":42,"passed_time":0.02907311439,"remaining_time":0.03853877954},
{"learn":[5.150086026],"iteration":43,"passed_time":0.02967344994,"remaining_time":0.03776620902},
{"learn":[5.129541522],"iteration":44,"passed_time":0.0306033321,"remaining_time":0.03740407256},
{"learn":[5.112457868],"iteration":45,"passed_time":0.03127591967,"remaining_time":0.03671521005},
{"learn":[5.095497116],"iteration":46,"passed_time":0.03219813279,"remaining_time":0.03630853272},
{"learn":[5.083931009],"iteration":47,"passed_time":0.03270623234,"remaining_time":0.0354317517},
{"learn":[5.071700826],"iteration":48,"passed_time":0.03331965201,"remaining_time":0.03467963781},
{"learn":[5.059779504],"iteration":49,"passed_time":0.0340824831,"remaining_time":0.0340824831},
{"learn":[5.049868736],"iteration":50,"passed_time":0.03449125746,"remaining_time":0.03313865913},
{"learn":[5.036484393],"iteration":51,"passed_time":0.03550905368,"remaining_time":0.03277758801},
{"learn":[5.022683719],"iteration":52,"passed_time":0.03628855216,"remaining_time":0.03218041418},
{"learn":[5.011471291],"iteration":53,"passed_time":0.03775082827,"remaining_time":0.03215811297},
{"learn":[4.992729352],"iteration":54,"passed_time":0.03833509376,"remaining_time":0.03136507672},
{"learn":[4.985142965],"iteration":55,"passed_time":0.03897673888,"remaining_time":0.03062458054},
{"learn":[4.97476452],"iteration":56,"passed_time":0.03997059217,"remaining_time":0.03015325374},
{"learn":[4.959104144],"iteration":57,"passed_time":0.04068381832,"remaining_time":0.02946069602},
{"learn":[4.944984792],"iteration":58,"passed_time":0.04133569662,"remaining_time":0.02872480613},
{"learn":[4.939044395],"iteration":59,"passed_time":0.04228457006,"remaining_time":0.02818971337},
{"learn":[4.92988468],"iteration":60,"passed_time":0.04283490715,"remaining_time":0.02738625211},
{"learn":[4.91290903],"iteration":61,"passed_time":0.04347129042,"remaining_time":0.02664369413},
{"learn":[4.903453846],"iteration":62,"passed_time":0.04473691645,"remaining_time":0.02627406204},
{"learn":[4.887097247],"iteration":63,"passed_time":0.04567257968,"remaining_time":0.02569082607},
{"learn":[4.877095112],"iteration":64,"passed_time":0.04625697201,"remaining_time":0.02490760031},
{"learn":[4.865705242],"iteration":65,"passed_time":0.04690061518,"remaining_time":0.02416092297},
{"learn":[4.848373223],"iteration":66,"passed_time":0.04751665666,"remaining_time":0.02340372641},
{"learn":[4.841751929],"iteration":67,"passed_time":0.04804338745,"remaining_time":0.02260865292},
{"learn":[4.839750657],"iteration":68,"passed_time":0.048603257,"remaining_time":0.0218362459},
{"learn":[4.826983884],"iteration":69,"passed_time":0.04917318234,"remaining_time":0.021074221},
{"learn":[4.817256399],"iteration":70,"passed_time":0.04979756161,"remaining_time":0.02033984911},
{"learn":[4.805652168],"iteration":71,"passed_time":0.05038541447,"remaining_time":0.01959432785},
{"learn":[4.794595544],"iteration":72,"passed_time":0.0510328161,"remaining_time":0.01887515116},
{"learn":[4.788554224],"iteration":73,"passed_time":0.05167282505,"remaining_time":0.01815531691},
{"learn":[4.7848235],"iteration":74,"passed_time":0.05228405362,"remaining_time":0.01742801787},
{"learn":[4.774765541],"iteration":75,"passed_time":0.05290652074,"remaining_time":0.01670732234},
{"learn":[4.766864552],"iteration":76,"passed_time":0.05378365208,"remaining_time":0.01606524673},
{"learn":[4.756563023],"iteration":77,"passed_time":0.05447656805,"remaining_time":0.01536518586},
{"learn":[4.747519024],"iteration":78,"passed_time":0.05514755442,"remaining_time":0.01465947649},
{"learn":[4.73589735],"iteration":79,"passed_time":0.05608794464,"remaining_time":0.01402198616},
{"learn":[4.726535412],"iteration":80,"passed_time":0.05669607458,"remaining_time":0.01329907922},
{"learn":[4.720560277],"iteration":81,"passed_time":0.05731137106,"remaining_time":0.01258054487},
{"learn":[4.712542766],"iteration":82,"passed_time":0.05792003956,"remaining_time":0.01186314063},
{"learn":[4.705191817],"iteration":83,"passed_time":0.05879598739,"remaining_time":0.01119923569},
{"learn":[4.703181409],"iteration":84,"passed_time":0.0594838963,"remaining_time":0.01049715817},
{"learn":[4.692675872],"iteration":85,"passed_time":0.06042099262,"remaining_time":0.009835975542},
{"learn":[4.688737373],"iteration":86,"passed_time":0.06110774628,"remaining_time":0.009131042548},
{"learn":[4.679027406],"iteration":87,"passed_time":0.0616851041,"remaining_time":0.008411605105},
{"learn":[4.673925842],"iteration":88,"passed_time":0.06227233992,"remaining_time":0.007696581338},
{"learn":[4.662890343],"iteration":89,"passed_time":0.06284104641,"remaining_time":0.006982338489},
{"learn":[4.655077576],"iteration":90,"passed_time":0.06333183511,"remaining_time":0.006263588087},
{"learn":[4.645436176],"iteration":91,"passed_time":0.06383294441,"remaining_time":0.005550690818},
{"learn":[4.63567781],"iteration":92,"passed_time":0.06450223845,"remaining_time":0.004855007195},
{"learn":[4.627948492],"iteration":93,"passed_time":0.06523739346,"remaining_time":0.004164088944},
{"learn":[4.618285529],"iteration":94,"passed_time":0.06586332297,"remaining_time":0.003466490683},
{"learn":[4.61190616],"iteration":95,"passed_time":0.0665435409,"remaining_time":0.002772647538},
{"learn":[4.602782785],"iteration":96,"passed_time":0.06744453073,"remaining_time":0.002085913322},
{"learn":[4.60010226],"iteration":97,"passed_time":0.06795650293,"remaining_time":0.001386867407},
{"learn":[4.589218848],"iteration":98,"passed_time":0.06851406162,"remaining_time":0.0006920612285},
{"learn":[4.584272539],"iteration":99,"passed_time":0.06905151768,"remaining_time":0}
]}